Components/MUX2.sv
(* dont_merge *) module MUX2
#(
  parameter DATA_PACKET_SIZE = 10
)
(
    input clk,
	 input reset,
    input [(DATA_PACKET_SIZE-1):0] data_1,
	 input [(DATA_PACKET_SIZE-1):0] data_2,
	 input select,
	 
	 output reg [(DATA_PACKET_SIZE-1):0] out
);

 always@(posedge clk)
 begin
   if(reset)
	   out <='bz;
   else
    begin	
		  if(select===0)
			  out <= data_1;
		  else
		   if(select===1)  
			  out <= data_2;
		   else
		     if(select===1'bx)
		        out <='bx;
			 else
			   if(select===1'bz)
	     	      out <='bz;
 	 end 
 end

endmodule

Components/MUX2/MUX2NewTB.sv
`timescale 1ns / 1ps
//////////////////////////////////////////////////////////////////////////////////
// Company: 
// Engineer: 
// 
// Create Date: 03/16/2021 08:37:43 PM
// Design Name: 
// Module Name: MUX2NewTB
// Project Name: 
// Target Devices: 
// Tool Versions: 
// Description: 
// 
// Dependencies: 
// 
// Revision:
// Revision 0.01 - File Created
// Additional Comments:
// 
//////////////////////////////////////////////////////////////////////////////////


module MUX2NewTB();
  localparam DATA_PACKET_SIZE = 4;
  localparam period = 2;
  
  logic clk;
  logic reset;
  logic [(DATA_PACKET_SIZE-1):0] data_1;
  logic [(DATA_PACKET_SIZE-1):0] data_2;
  logic select;
 
  logic [(DATA_PACKET_SIZE-1):0] out;
  
  
  MUX2 
   #(.DATA_PACKET_SIZE(DATA_PACKET_SIZE))
  DUT(
     .clk(clk),
     .reset(reset),
     .data_1(data_1),
     .data_2(data_2),
     .select(select),
     .out(out)
  );
  
  function logic [(DATA_PACKET_SIZE-1):0] checkMux(logic select, logic [(DATA_PACKET_SIZE-1):0] data_1, logic [(DATA_PACKET_SIZE-1):0] data_2 );
    if(select === 0)
       return data_1;
    else
     if(select === 1)
       return data_2;
     else
      if(select === 1'bx)
        return 'bx; 
      else
        if(select === 1'bz)
           return 'bz;  
  endfunction
  
  initial begin
    $dumpfile("MUX2.vcd");
    $dumpvars(1, MUX2NewTB); 
  end
  
  initial begin
    clk <= 0;
    reset <= 0;
    data_1 <= 0;
    data_2 <= 0;
    select <= 0;
  end
  
  always begin
    #(period/2) clk <= ~clk;
  end

  always@(posedge clk) begin //Here we test all possible input combinations without x and z
       #(period)
      if( (data_1 == (2**DATA_PACKET_SIZE -1))&&(data_2 == (2**DATA_PACKET_SIZE -1)) ) begin
            if(select == 0)
               select <= 1;
               
            if(select == 1)
               select <= 1'bz;
               
            if(select === 1'bz)
               select <= 1'bx;    
             
            if(select === 1'bx)
                 $finish;   
               
            data_1 <= 0;
            data_2 <= 0;
      end
          
      if( data_1 < (2**DATA_PACKET_SIZE -1) )    
          data_1 <= data_1 + 1;
      
      if( data_1 == (2**DATA_PACKET_SIZE -1) )
         if( data_2 < (2**DATA_PACKET_SIZE -1) )
             data_2 <= data_2 + 1;
            
      
  end 
  
   always@(posedge clk) begin
   
      #(period)
      assert(out===checkMux(select, data_1, data_2) ) $display("[time=%0t] TEST PASSED for inputs select =%0d -- data_1=%0d -- data_2=%0d ### out=%0d",$time,select,data_1,data_2,out );
      else
        $display("[time=%0t] TEST FAILED for inputs select =%0d -- data_1=%0d -- data_2=%0d ### out=%0d instead of %0d",$time,select,data_1,data_2, out,checkMux(select, data_1, data_2)); 
          
   end

endmodule

Components/MUX2/MUX2.vcd
$date
   Tue Mar 16 22:18:08 2021
$end
$version
  2019.1
$end
$timescale
  1ps
$end
$scope module MUX2NewTB $end
$var reg 1 ! clk $end
$var reg 1 " reset $end
$var reg 4 # data_1 [3:0] $end
$var reg 4 $ data_2 [3:0] $end
$var reg 1 % select $end
$var reg 4 & out [3:0] $end
$var parameter 32 ' DATA_PACKET_SIZE [31:0] $end
$var parameter 32 ( period [31:0] $end
$upscope $end
$enddefinitions $end
#0
$dumpvars
0!
0"
b0 #
b0 $
0%
bx &
b100 '
b10 (
$end
#1000
1!
b0 &
#2000
0!
#3000
1!
b1 #
b1 &
#4000
0!
#5000
1!
b10 #
b10 &
#6000
0!
#7000
1!
b11 #
b11 &
#8000
0!
#9000
1!
b100 #
b100 &
#10000
0!
#11000
1!
b101 #
b101 &
#12000
0!
#13000
1!
b110 #
b110 &
#14000
0!
#15000
1!
b111 #
b111 &
#16000
0!
#17000
1!
b1000 #
b1000 &
#18000
0!
#19000
1!
b1001 #
b1001 &
#20000
0!
#21000
1!
b1010 #
b1010 &
#22000
0!
#23000
1!
b1011 #
b1011 &
#24000
0!
#25000
1!
b1100 #
b1100 &
#26000
0!
#27000
1!
b1101 #
b1101 &
#28000
0!
#29000
1!
b1110 #
b1110 &
#30000
0!
#31000
1!
b1111 #
b1111 &
#32000
0!
#33000
1!
b1 $
b1111 &
#34000
0!
#35000
1!
b10 $
b1111 &
#36000
0!
#37000
1!
b11 $
b1111 &
#38000
0!
#39000
1!
b100 $
b1111 &
#40000
0!
#41000
1!
b101 $
b1111 &
#42000
0!
#43000
1!
b110 $
b1111 &
#44000
0!
#45000
1!
b111 $
b1111 &
#46000
0!
#47000
1!
b1000 $
b1111 &
#48000
0!
#49000
1!
b1001 $
b1111 &
#50000
0!
#51000
1!
b1010 $
b1111 &
#52000
0!
#53000
1!
b1011 $
b1111 &
#54000
0!
#55000
1!
b1100 $
b1111 &
#56000
0!
#57000
1!
b1101 $
b1111 &
#58000
0!
#59000
1!
b1110 $
b1111 &
#60000
0!
#61000
1!
b1111 $
b1111 &
#62000
0!
#63000
1!
b0 #
b0 $
1%
b0 &
#64000
0!
#65000
1!
b1 #
b0 &
#66000
0!
#67000
1!
b10 #
b0 &
#68000
0!
#69000
1!
b11 #
b0 &
#70000
0!
#71000
1!
b100 #
b0 &
#72000
0!
#73000
1!
b101 #
b0 &
#74000
0!
#75000
1!
b110 #
b0 &
#76000
0!
#77000
1!
b111 #
b0 &
#78000
0!
#79000
1!
b1000 #
b0 &
#80000
0!
#81000
1!
b1001 #
b0 &
#82000
0!
#83000
1!
b1010 #
b0 &
#84000
0!
#85000
1!
b1011 #
b0 &
#86000
0!
#87000
1!
b1100 #
b0 &
#88000
0!
#89000
1!
b1101 #
b0 &
#90000
0!
#91000
1!
b1110 #
b0 &
#92000
0!
#93000
1!
b1111 #
b0 &
#94000
0!
#95000
1!
b1 $
b1 &
#96000
0!
#97000
1!
b10 $
b10 &
#98000
0!
#99000
1!
b11 $
b11 &
#100000
0!
#101000
1!
b100 $
b100 &
#102000
0!
#103000
1!
b101 $
b101 &
#104000
0!
#105000
1!
b110 $
b110 &
#106000
0!
#107000
1!
b111 $
b111 &
#108000
0!
#109000
1!
b1000 $
b1000 &
#110000
0!
#111000
1!
b1001 $
b1001 &
#112000
0!
#113000
1!
b1010 $
b1010 &
#114000
0!
#115000
1!
b1011 $
b1011 &
#116000
0!
#117000
1!
b1100 $
b1100 &
#118000
0!
#119000
1!
b1101 $
b1101 &
#120000
0!
#121000
1!
b1110 $
b1110 &
#122000
0!
#123000
1!
b1111 $
b1111 &
#124000
0!
#125000
1!
b0 #
b0 $
z%
bz &
#126000
0!
#127000
1!
b1 #
bz &
#128000
0!
#129000
1!
b10 #
bz &
#130000
0!
#131000
1!
b11 #
bz &
#132000
0!
#133000
1!
b100 #
bz &
#134000
0!
#135000
1!
b101 #
bz &
#136000
0!
#137000
1!
b110 #
bz &
#138000
0!
#139000
1!
b111 #
bz &
#140000
0!
#141000
1!
b1000 #
bz &
#142000
0!
#143000
1!
b1001 #
bz &
#144000
0!
#145000
1!
b1010 #
bz &
#146000
0!
#147000
1!
b1011 #
bz &
#148000
0!
#149000
1!
b1100 #
bz &
#150000
0!
#151000
1!
b1101 #
bz &
#152000
0!
#153000
1!
b1110 #
bz &
#154000
0!
#155000
1!
b1111 #
bz &
#156000
0!
#157000
1!
b1 $
bz &
#158000
0!
#159000
1!
b10 $
bz &
#160000
0!
#161000
1!
b11 $
bz &
#162000
0!
#163000
1!
b100 $
bz &
#164000
0!
#165000
1!
b101 $
bz &
#166000
0!
#167000
1!
b110 $
bz &
#168000
0!
#169000
1!
b111 $
bz &
#170000
0!
#171000
1!
b1000 $
bz &
#172000
0!
#173000
1!
b1001 $
bz &
#174000
0!
#175000
1!
b1010 $
bz &
#176000
0!
#177000
1!
b1011 $
bz &
#178000
0!
#179000
1!
b1100 $
bz &
#180000
0!
#181000
1!
b1101 $
bz &
#182000
0!
#183000
1!
b1110 $
bz &
#184000
0!
#185000
1!
b1111 $
bz &
#186000
0!
#187000
1!
b0 #
b0 $
x%
bx &
#188000
0!
#189000
1!
b1 #
bx &
#190000
0!
#191000
1!
b10 #
bx &
#192000
0!
#193000
1!
b11 #
bx &
#194000
0!
#195000
1!
b100 #
bx &
#196000
0!
#197000
1!
b101 #
bx &
#198000
0!
#199000
1!
b110 #
bx &
#200000
0!
#201000
1!
b111 #
bx &
#202000
0!
#203000
1!
b1000 #
bx &
#204000
0!
#205000
1!
b1001 #
bx &
#206000
0!
#207000
1!
b1010 #
bx &
#208000
0!
#209000
1!
b1011 #
bx &
#210000
0!
#211000
1!
b1100 #
bx &
#212000
0!
#213000
1!
b1101 #
bx &
#214000
0!
#215000
1!
b1110 #
bx &
#216000
0!
#217000
1!
b1111 #
bx &
#218000
0!
#219000
1!
b1 $
bx &
#220000
0!
#221000
1!
b10 $
bx &
#222000
0!
#223000
1!
b11 $
bx &
#224000
0!
#225000
1!
b100 $
bx &
#226000
0!
#227000
1!
b101 $
bx &
#228000
0!
#229000
1!
b110 $
bx &
#230000
0!
#231000
1!
b111 $
bx &
#232000
0!
#233000
1!
b1000 $
bx &
#234000
0!
#235000
1!
b1001 $
bx &
#236000
0!
#237000
1!
b1010 $
bx &
#238000
0!
#239000
1!
b1011 $
bx &
#240000
0!
#241000
1!
b1100 $
bx &
#242000
0!
#243000
1!
b1101 $
bx &
#244000
0!
#245000
1!
b1110 $
bx &
#246000
0!
#247000
1!
b1111 $
bx &
